{
    "participant_id": {
        "LongName": "Participant Identifier",
        "Description": "Unique BIDS identifier for the participant in this study."
    },
    "MET_TRYP": {
        "LongName": "Plasma Tryptophan",
        "Description": "TRYP nM/ml"
    },
    "MET_TYR": {
        "LongName": "Plasma LNAA Tyrosine",
        "Description": "TYR_nM/ml"
    },
    "MET_VAL": {
        "LongName": "Valine",
        "Description": "VAL nM/ml"
    },
    "MET_ISOLEU": {
        "LongName": "Iso-Leucine",
        "Description": "ISOLEU  nM/ml"
    },
    "MET_LEU": {
        "LongName": "Leucine",
        "Description": "LEU  nM/ml"
    },
    "MET_PHE": {
        "LongName": "Phenylalanine HPLC",
        "Description": "PHE  nM/ml"
    },
    "MET_QUIN": {
        "LongName": "Quinolinic Acid",
        "Description": "QUIN  nM/ml"
    }
}